monty_hall_simulator_2016/__init__.py
monty_hall_simulator_2016/game.py
monty_hall_simulator_2016/main.py
monty_hall_simulator_2016/simulator.py
monty_hall_simulator_2016-0.1.dist-info/DESCRIPTION.rst
monty_hall_simulator_2016-0.1.dist-info/METADATA
monty_hall_simulator_2016-0.1.dist-info/RECORD
monty_hall_simulator_2016-0.1.dist-info/WHEEL
monty_hall_simulator_2016-0.1.dist-info/entry_points.txt
monty_hall_simulator_2016-0.1.dist-info/metadata.json
monty_hall_simulator_2016-0.1.dist-info/top_level.txt
