Metadata-Version: 2.0
Name: monty-hall-simulator-2016
Version: 0.1
Summary: Still don't believe you should switch?
Home-page: https://github.com/lawrencehlee/monty_hall_simulator_2016
Author: Lawrence H Lee
Author-email: lee.lawrenceh@gmail.com
License: MIT
Platform: UNKNOWN
Requires-Dist: Click
